pyspecty/__init__.py
pyspecty/error_hook.py
pyspecty-1.0.dist-info/LICENSE
pyspecty-1.0.dist-info/METADATA
pyspecty-1.0.dist-info/WHEEL
pyspecty-1.0.dist-info/top_level.txt
pyspecty-1.0.dist-info/RECORD
