Metadata-Version: 2.1
Name: pyspecty
Version: 1.0
Summary: A happy light weight library to search python errors on stackoverflow automatically.
Home-page: https://github.com/iam-mhaseeb/pyspecty
Author: Muhammad Haseeb
Author-email: haseeb.emailbox@gmail.com
License: MIT
Keywords: python,errors,debugging
Platform: UNKNOWN
Requires-Dist: singleton-decorator
